{
    "arch": {
        "arch": "x64"
    },
    "segments": [
        {
            "end": 4198400,
            "content_file": "8b8254e023dc8002882ec427510bfc3b.bin",
            "start": 4194304,
            "permissions": {
                "r": true,
                "x": true,
                "w": false
            },
            "name": "/home/b1ngo/firmcorn/t1"
        },
        {
            "end": 6295552,
            "content_file": "635d1207f2432c5f11e68c91ff50d960.bin",
            "start": 6291456,
            "permissions": {
                "r": true,
                "x": false,
                "w": false
            },
            "name": "/home/b1ngo/firmcorn/t1"
        },
        {
            "end": 6299648,
            "content_file": "fcedd097fea78930332f0983756be295.bin",
            "start": 6295552,
            "permissions": {
                "r": true,
                "x": false,
                "w": true
            },
            "name": "/home/b1ngo/firmcorn/t1"
        },
        {
            "end": 140737349734400,
            "content_file": "9c7da235bf729726f3f67910af5d683a.bin",
            "start": 140737347899392,
            "permissions": {
                "r": true,
                "x": true,
                "w": false
            },
            "name": "/lib/x86_64-linux-gnu/libc-2.23.so"
        },
        {
            "end": 140737351831552,
            "content_file": "",
            "start": 140737349734400,
            "permissions": {
                "r": false,
                "x": false,
                "w": false
            },
            "name": "/lib/x86_64-linux-gnu/libc-2.23.so"
        },
        {
            "end": 140737351847936,
            "content_file": "0b1e5e608d8cc5e3021e18b1120d30ea.bin",
            "start": 140737351831552,
            "permissions": {
                "r": true,
                "x": false,
                "w": false
            },
            "name": "/lib/x86_64-linux-gnu/libc-2.23.so"
        },
        {
            "end": 140737351856128,
            "content_file": "bbc5c52f715094394374b4222f33c26d.bin",
            "start": 140737351847936,
            "permissions": {
                "r": true,
                "x": false,
                "w": true
            },
            "name": "/lib/x86_64-linux-gnu/libc-2.23.so"
        },
        {
            "end": 140737351872512,
            "content_file": "f38a4550c1e3fdbcffd1145a292a2b75.bin",
            "start": 140737351856128,
            "permissions": {
                "r": true,
                "x": false,
                "w": true
            },
            "name": ""
        },
        {
            "end": 140737352028160,
            "content_file": "a61d869ff50cbc879e477616275edd4e.bin",
            "start": 140737351872512,
            "permissions": {
                "r": true,
                "x": true,
                "w": false
            },
            "name": "/lib/x86_64-linux-gnu/ld-2.23.so"
        },
        {
            "end": 140737353887744,
            "content_file": "792da964af0d44105af9959118c64869.bin",
            "start": 140737353875456,
            "permissions": {
                "r": true,
                "x": false,
                "w": true
            },
            "name": ""
        },
        {
            "end": 140737354113024,
            "content_file": "",
            "start": 140737354100736,
            "permissions": {
                "r": true,
                "x": false,
                "w": false
            },
            "name": "[vvar]"
        },
        {
            "end": 140737354121216,
            "content_file": "eb30ccc16e3c7c9a3188c217377feb67.bin",
            "start": 140737354113024,
            "permissions": {
                "r": true,
                "x": true,
                "w": false
            },
            "name": "[vdso]"
        },
        {
            "end": 140737354125312,
            "content_file": "6addc262f85071f33ddf9a49c44bcf87.bin",
            "start": 140737354121216,
            "permissions": {
                "r": true,
                "x": false,
                "w": false
            },
            "name": "/lib/x86_64-linux-gnu/ld-2.23.so"
        },
        {
            "end": 140737354129408,
            "content_file": "a131d7f2a5cda580e3f2e09c0011372b.bin",
            "start": 140737354125312,
            "permissions": {
                "r": true,
                "x": false,
                "w": true
            },
            "name": "/lib/x86_64-linux-gnu/ld-2.23.so"
        },
        {
            "end": 140737354133504,
            "content_file": "564fa9c292ea2339cf881b404b679b3b.bin",
            "start": 140737354129408,
            "permissions": {
                "r": true,
                "x": false,
                "w": true
            },
            "name": ""
        },
        {
            "end": 140737488351232,
            "content_file": "99d82f4e301f07902c298eb37a2398dc.bin",
            "start": 140737488216064,
            "permissions": {
                "r": true,
                "x": false,
                "w": true
            },
            "name": "[stack]"
        },
        {
            "end": 18446744073699069952,
            "content_file": "f50fc8acf66ee2f3fbbf8e270dcfe791.bin",
            "start": 18446744073699065856,
            "permissions": {
                "r": true,
                "x": true,
                "w": false
            },
            "name": "[vsyscall]"
        }
    ],
    "regs": {
        "al": 18446744073709551606,
        "r8": 4196048,
        "ah": 5,
        "rip": 4195830,
        "r13": 140737488346144,
        "bpl": 96,
        "ds": 0,
        "cs": 51,
        "fs": 0,
        "eflags": 582,
        "dx": 18446744073709542456,
        "sil": 40,
        "dh": 18446744073709551580,
        "rax": 4195830,
        "si": 18446744073709542440,
        "rbp": 4195936,
        "rcx": 0,
        "r9": 140737351940784,
        "bl": 0,
        "r12": 4195584,
        "ch": 0,
        "bx": 0,
        "es": 0,
        "ax": 1526,
        "dl": 56,
        "spl": 72,
        "rsi": 140737488346152,
        "r15": 0,
        "fsbase": 140737353881344,
        "r10": 2118,
        "gs": 0,
        "di": 1,
        "rsp": 140737488345928,
        "rdx": 140737488346168,
        "cl": 0,
        "rbx": 0,
        "sp": 140737488345928,
        "ip": null,
        "gsbase": 0,
        "bh": 0,
        "ss": 43,
        "rdi": 1,
        "r14": 0,
        "bp": 1632,
        "r11": 140737348032320,
        "cx": 0,
        "dil": 1
    }
}